[
    {
        "isSender": false,
        "date": "2022-12-18",
        "message": "pariatur ullamco eu non occaecat ut sint laboris aute nostrud laboris officia laborum laborum pariatur pariatur et pariatur ex"
    },
    {
        "isSender": true,
        "date": "2022-09-11",
        "message": "dolore eiusmod in"
    },
    {
        "isSender": true,
        "date": "2022-11-10",
        "message": "elit Lorem consectetur sit elit incididunt non sit incididunt excepteur laboris nisi ullamco voluptate exercitation ex minim enim reprehenderit ullamco"
    },
    {
        "isSender": false,
        "date": "2022-12-16",
        "message": "nostrud minim deserunt exercitation ut reprehenderit aliqua sunt occaecat cillum esse nulla in"
    },
    {
        "isSender": true,
        "date": "2022-05-05",
        "message": ""
    },
    {
        "isSender": true,
        "date": "2023-01-03",
        "message": "ullamco qui ad laboris tempor"
    },
    {
        "isSender": false,
        "date": "2022-10-08",
        "message": "aliqua sint aute et nulla deserunt culpa adipisicing duis consectetur cupidatat nostrud qui laboris tempor et eu laboris exercitation est"
    },
    {
        "isSender": false,
        "date": "2022-09-05",
        "message": ""
    },
    {
        "isSender": false,
        "date": "2022-03-23",
        "message": "enim nisi eu velit"
    },
    {
        "isSender": true,
        "date": "2022-10-05",
        "message": "excepteur quis incididunt voluptate sit voluptate sint"
    },
    {
        "isSender": false,
        "date": "2022-09-12",
        "message": "aliquip magna ipsum officia minim irure aute nisi"
    },
    {
        "isSender": false,
        "date": "2022-11-06",
        "message": "ipsum id mollit esse occaecat consequat sint occaecat elit eiusmod proident eu cupidatat anim"
    },
    {
        "isSender": false,
        "date": "2022-12-24",
        "message": "deserunt sunt nulla commodo commodo duis minim cupidatat non exercitation magna irure exercitation reprehenderit"
    },
    {
        "isSender": true,
        "date": "2022-11-04",
        "message": "dolore laborum officia aliqua excepteur"
    },
    {
        "isSender": false,
        "date": "2022-03-19",
        "message": "culpa cupidatat ut esse velit ea quis reprehenderit ex velit enim culpa veniam laboris reprehenderit deserunt dolore ea"
    },
    {
        "isSender": true,
        "date": "2022-06-14",
        "message": "irure cupidatat id"
    },
    {
        "isSender": false,
        "date": "2022-10-04",
        "message": "sunt sunt magna commodo incididunt dolore minim aliqua irure incididunt cillum Lorem fugiat occaecat aliquip cupidatat"
    },
    {
        "isSender": true,
        "date": "2022-12-25",
        "message": "cillum fugiat ad excepteur ad ea commodo non aliqua ut nostrud et mollit Lorem culpa anim amet non eu"
    },
    {
        "isSender": false,
        "date": "2022-12-13",
        "message": "dolor adipisicing culpa sint occaecat in aliqua cillum occaecat labore velit amet laboris duis fugiat commodo cillum incididunt aliqua"
    },
    {
        "isSender": false,
        "date": "2022-03-08",
        "message": "occaecat enim elit culpa"
    },
    {
        "isSender": true,
        "date": "2022-10-16",
        "message": "sunt anim culpa labore sit nulla et laboris id deserunt ex id in eiusmod Lorem excepteur mollit mollit laboris"
    },
    {
        "isSender": false,
        "date": "2022-12-12",
        "message": "cillum enim officia culpa ipsum reprehenderit veniam anim eiusmod excepteur amet labore nostrud ex"
    },
    {
        "isSender": false,
        "date": "2022-05-30",
        "message": "eu veniam laborum eu laborum labore occaecat labore"
    },
    {
        "isSender": true,
        "date": "2022-03-03",
        "message": "non exercitation ullamco adipisicing nisi ea"
    },
    {
        "isSender": false,
        "date": "2022-11-18",
        "message": "consequat eiusmod culpa ipsum esse anim"
    },
    {
        "isSender": false,
        "date": "2022-08-09",
        "message": "veniam est aute"
    },
    {
        "isSender": true,
        "date": "2022-06-06",
        "message": "laboris esse enim mollit eiusmod est officia fugiat duis sit quis reprehenderit mollit laboris ad eiusmod sint ea magna eiusmod"
    },
    {
        "isSender": false,
        "date": "2022-03-29",
        "message": "nulla veniam labore duis ullamco pariatur reprehenderit adipisicing adipisicing do ullamco"
    },
    {
        "isSender": false,
        "date": "2022-05-18",
        "message": "quis est elit est ex exercitation"
    },
    {
        "isSender": true,
        "date": "2022-04-22",
        "message": "laborum enim dolor mollit anim minim non est irure elit aliqua voluptate proident non nostrud mollit"
    },
    {
        "isSender": true,
        "date": "2022-07-15",
        "message": "ut qui sunt sit commodo nulla anim esse est et tempor sint irure laborum"
    },
    {
        "isSender": true,
        "date": "2022-10-08",
        "message": "ullamco commodo officia enim consequat quis amet consequat elit enim elit enim nostrud adipisicing id dolore labore est nulla veniam"
    },
    {
        "isSender": false,
        "date": "2022-07-14",
        "message": "et nisi sit eu deserunt Lorem"
    },
    {
        "isSender": true,
        "date": "2023-02-06",
        "message": "officia adipisicing exercitation fugiat tempor ipsum est eu nulla adipisicing veniam irure sunt sunt ipsum excepteur ea tempor"
    },
    {
        "isSender": true,
        "date": "2022-02-20",
        "message": "commodo eiusmod sit deserunt ut deserunt adipisicing ad ut"
    },
    {
        "isSender": true,
        "date": "2022-11-19",
        "message": "commodo commodo"
    },
    {
        "isSender": true,
        "date": "2022-09-17",
        "message": "nulla sint elit laboris ut laboris occaecat occaecat laborum quis enim laborum occaecat in magna laborum velit"
    },
    {
        "isSender": true,
        "date": "2022-07-01",
        "message": "eiusmod excepteur sunt officia nulla aliquip anim eiusmod minim quis aliqua aliquip ex nulla Lorem minim dolor"
    },
    {
        "isSender": true,
        "date": "2022-06-19",
        "message": "voluptate commodo sunt nulla anim officia"
    },
    {
        "isSender": true,
        "date": "2022-11-19",
        "message": "ut non labore ullamco fugiat excepteur dolor excepteur laboris cillum eiusmod"
    },
    {
        "isSender": false,
        "date": "2022-04-01",
        "message": "nostrud eu consequat"
    },
    {
        "isSender": false,
        "date": "2022-11-02",
        "message": "adipisicing excepteur fugiat deserunt aute occaecat commodo duis"
    },
    {
        "isSender": true,
        "date": "2023-01-28",
        "message": "anim magna non exercitation ea nulla cillum duis eiusmod sunt aute"
    },
    {
        "isSender": true,
        "date": "2023-01-11",
        "message": "voluptate amet exercitation id nulla irure incididunt cupidatat cupidatat ut anim culpa occaecat"
    },
    {
        "isSender": true,
        "date": "2022-04-22",
        "message": "pariatur adipisicing incididunt voluptate"
    },
    {
        "isSender": true,
        "date": "2022-08-11",
        "message": "culpa reprehenderit Lorem ipsum elit excepteur culpa quis nostrud proident reprehenderit ea consequat consequat eiusmod do ex"
    },
    {
        "isSender": false,
        "date": "2022-05-02",
        "message": "mollit exercitation cillum non excepteur culpa dolor eiusmod ut ullamco"
    },
    {
        "isSender": false,
        "date": "2022-08-13",
        "message": "et ea sunt consequat voluptate esse magna ex elit irure"
    },
    {
        "isSender": false,
        "date": "2022-03-24",
        "message": "officia eu"
    },
    {
        "isSender": false,
        "date": "2022-04-04",
        "message": "amet"
    }
]